xilinx_language_server/__init__.py
xilinx_language_server/__main__.py
xilinx_language_server/_metainfo.py
xilinx_language_server/_version.py
xilinx_language_server/py.typed
xilinx_language_server/server.py
xilinx_language_server/assets/json/vivado.json
xilinx_language_server/assets/json/xsct.json
xilinx_language_server-0.0.4.data/data/share/bash-completion/completions/xilinx-language-server
xilinx_language_server-0.0.4.data/data/share/man/man1/xilinx-language-server.1
xilinx_language_server-0.0.4.data/data/share/zsh/site-functions/_xilinx-language-server
xilinx_language_server-0.0.4.dist-info/LICENSE
xilinx_language_server-0.0.4.dist-info/METADATA
xilinx_language_server-0.0.4.dist-info/WHEEL
xilinx_language_server-0.0.4.dist-info/entry_points.txt
xilinx_language_server-0.0.4.dist-info/top_level.txt
xilinx_language_server-0.0.4.dist-info/RECORD
