Metadata-Version: 2.1
Name: xilinx-language-server
Version: 0.0.4
Summary: xilinx language server
Author-email: Wu Zhenyu <wuzhenyu@ustc.edu>
License: GPL v3
Project-URL: Homepage, https://xilinx-language-server.readthedocs.io
Project-URL: Download, https://github.com/Freed-Wu/xilinx-language-server/releases
Project-URL: Bug Report, https://github.com/Freed-Wu/xilinx-language-server/issues
Project-URL: Source, https://github.com/Freed-Wu/xilinx-language-server
Keywords: xilinx,language server
Classifier: Development Status :: 3 - Alpha
Classifier: Intended Audience :: Developers
Classifier: Topic :: Software Development :: Build Tools
Classifier: License :: OSI Approved :: GNU General Public License v3 (GPLv3)
Classifier: Operating System :: Microsoft :: Windows
Classifier: Operating System :: POSIX
Classifier: Operating System :: Unix
Classifier: Operating System :: MacOS
Classifier: Programming Language :: Python :: 3 :: Only
Classifier: Programming Language :: Python :: 3
Classifier: Programming Language :: Python :: 3.7
Classifier: Programming Language :: Python :: 3.8
Classifier: Programming Language :: Python :: 3.9
Classifier: Programming Language :: Python :: 3.10
Classifier: Programming Language :: Python :: 3.11
Classifier: Programming Language :: Python :: Implementation :: CPython
Classifier: Programming Language :: Python :: Implementation :: PyPy
Requires-Python: >=3.7
License-File: LICENSE
Requires-Dist: platformdirs
Requires-Dist: pygls
Provides-Extra: dev
Requires-Dist: neovim ; extra == 'dev'
Requires-Dist: pytest-cov ; extra == 'dev'
